dagster_ssis/__init__.py
dagster_ssis/sql_server_resource.py
dagster_ssis/mssql_jobs/__init__.py
dagster_ssis/mssql_jobs/mssql_job_assets.py
dagster_ssis/mssql_jobs/mssql_job_sensor.py
dagster_ssis/ssis/__init__.py
dagster_ssis/ssis/ssis_assets.py
dagster_ssis/ssis/ssis_sensor.py
dagster_ssis-0.0.1.dist-info/METADATA
dagster_ssis-0.0.1.dist-info/WHEEL
dagster_ssis-0.0.1.dist-info/licenses/LICENSE
dagster_ssis-0.0.1.dist-info/RECORD
