Metadata-Version: 2.4
Name: dagster-ssis
Version: 0.0.1
Project-URL: Homepage, https://github.com/cody-scott/dagster-ssis
Project-URL: Documentation, https://github.com/cody-scott/dagster-ssis/tree/main/docs
Project-URL: Repository, https://github.com/cody-scott/dagster-ssis.git
Project-URL: Issues, https://github.com/cody-scott/dagster-ssis/issues
Author-email: Cody Scott <carry-retort01@icloud.com>
License:                                  Apache License
License-File: LICENSE
Requires-Python: >=3.8
Requires-Dist: dagster
Requires-Dist: pyodbc
Requires-Dist: sqlalchemy
Provides-Extra: dev
Requires-Dist: black; extra == 'dev'
Requires-Dist: dagster-webserver; extra == 'dev'
Requires-Dist: pytest; extra == 'dev'
Requires-Dist: pytest-cov; extra == 'dev'
Requires-Dist: pytest-mock; extra == 'dev'
Requires-Dist: ruff; extra == 'dev'
